{
    "name": "Cosmos3D",
    "version": "02.01.01.00",
    "force_update": "0",
    "description": "Cosmos3D configurations",
    "machine_model_list": [
        {
            "name": "Cosmos3D X1",
            "sub_path": "machine/Cosmos3D X1.json"
        }
    ],
    "process_list": [
        {
            "name": "fdm_process_common",
            "sub_path": "process/fdm_process_common.json"
        },
		{
             "name": "Concrete Printing @Cosmos3D X1 60 nozzle",
             "sub_path": "process/Concrete Printing @Cosmos3D X1 60 nozzle.json"
        }
    ],
    "filament_list": [
        {
            "name": "fdm_filament_common",
            "sub_path": "filament/fdm_filament_common.json"
        },
        {
            "name": "fdm_filament_concrete",
            "sub_path": "filament/fdm_filament_concrete.json"
        },
        {
            "name": "Generic Concrete",
            "sub_path": "filament/Generic Concrete.json"
        }
    ],
    "machine_list": [
        {
            "name": "fdm_machine_common",
            "sub_path": "machine/fdm_machine_common.json"
        },
        {     
	        "name": "Cosmos3D X1 60 nozzle",
            "sub_path": "machine/Cosmos3D X1 60 nozzle.json"
        }
    ]
}
